README
pyafraid.py
setup.py
pyafraid.egg-info/PKG-INFO
pyafraid.egg-info/SOURCES.txt
pyafraid.egg-info/dependency_links.txt
pyafraid.egg-info/entry_points.txt
pyafraid.egg-info/top_level.txt