Metadata-Version: 1.0
Name: pyafraid
Version: 0.1
Summary: Command-line tool for manipulating afraid.org DDNS
Home-page: http://github.com/campbellr/pyafraid
Author: Ryan Campbell
Author-email: campbellr@gmail.com
License: UNKNOWN
Platform: UNKNOWN
